datafun/__init__.py
datafun/cache.py
datafun/dataset.py
datafun/utils.py
datafun/sources/__init__.py
datafun/sources/elk.py
datafun/sources/gcs.py
datafun/sources/iterable.py
datafun/sources/local_file.py
datafun/sources/rest.py
datafun-0.6.0.dist-info/LICENSE
datafun-0.6.0.dist-info/METADATA
datafun-0.6.0.dist-info/WHEEL
datafun-0.6.0.dist-info/top_level.txt
datafun-0.6.0.dist-info/RECORD
