Metadata-Version: 2.1
Name: datafun
Version: 0.6.0
Summary: datafun brings the fun back to data pipelines
Author-email: "Diego Giorgini, Luigi Di Sotto, Saeed Choobani" <diego.giorgini@aitechnologies.it>
Requires-Python: >=3.8
License-File: LICENSE
Requires-Dist: backoff
Requires-Dist: pydlib
Requires-Dist: tqdm
Requires-Dist: google-cloud-storage
Requires-Dist: elasticsearch <8
Requires-Dist: requests
